pdbstore/__init__.py
pdbstore/__main__.py
pdbstore/_version.py
pdbstore/config.py
pdbstore/const.py
pdbstore/exceptions.py
pdbstore/py.typed.py
pdbstore/typing.py
pdbstore/util.py
pdbstore/cli/__init__.py
pdbstore/cli/args.py
pdbstore/cli/boolean_action.py
pdbstore/cli/cli.py
pdbstore/cli/command.py
pdbstore/cli/exit_codes.py
pdbstore/cli/formatters.py
pdbstore/cli/once_argument.py
pdbstore/cli/smart_formatter.py
pdbstore/cli/commands/__init__.py
pdbstore/cli/commands/add.py
pdbstore/cli/commands/clean.py
pdbstore/cli/commands/del.py
pdbstore/cli/commands/fetch.py
pdbstore/cli/commands/promote.py
pdbstore/cli/commands/query.py
pdbstore/cli/commands/report.py
pdbstore/cli/commands/unused.py
pdbstore/io/__init__.py
pdbstore/io/cab.py
pdbstore/io/colors.py
pdbstore/io/file.py
pdbstore/io/output.py
pdbstore/io/pdbfile.py
pdbstore/io/portablepdbfile.py
pdbstore/report/__init__.py
pdbstore/report/base.py
pdbstore/report/file.py
pdbstore/report/generator.py
pdbstore/report/product.py
pdbstore/report/transaction.py
pdbstore/store/__init__.py
pdbstore/store/entry.py
pdbstore/store/history.py
pdbstore/store/store.py
pdbstore/store/summary.py
pdbstore/store/transaction.py
pdbstore/store/transaction_type.py
pdbstore/store/transactions.py
pdbstore/templates/README.md
pdbstore/templates/__init__.py
pdbstore/templates/html/files.tmpl
pdbstore/templates/html/products.tmpl
pdbstore/templates/html/transactions.tmpl
pdbstore/templates/json/files.tmpl
pdbstore/templates/json/products.tmpl
pdbstore/templates/json/transactions.tmpl
pdbstore/templates/markdown/files.tmpl
pdbstore/templates/markdown/products.tmpl
pdbstore/templates/markdown/transactions.tmpl
pdbstore/templates/text/files.tmpl
pdbstore/templates/text/products.tmpl
pdbstore/templates/text/transactions.tmpl
pdbstore-1.1.0.dist-info/AUTHORS.rst
pdbstore-1.1.0.dist-info/COPYING
pdbstore-1.1.0.dist-info/METADATA
pdbstore-1.1.0.dist-info/WHEEL
pdbstore-1.1.0.dist-info/entry_points.txt
pdbstore-1.1.0.dist-info/top_level.txt
pdbstore-1.1.0.dist-info/RECORD
