Metadata-Version: 2.1
Name: pdbstore
Version: 1.1.0
Summary: manage PDB and PE files through a local symbols store
Author-email: Jacques Raphanel <jrp@crabisoft.fr>
License: MIT
Project-URL: changelog, https://github.com/crabisoft/pdbstore/blob/main/CHANGELOG.md
Project-URL: documentation, https://pdbstore.readthedocs.io
Project-URL: homepage, https://github.com/crabisoft/pdbstore
Project-URL: issues, https://github.com/crabisoft/pdbstore/issues
Project-URL: repository, http://github.com/crabisoft/pdbstore.git
Keywords: development,symstore,pdb,pdbstore
Classifier: Development Status :: 5 - Production/Stable
Classifier: Environment :: Console
Classifier: Intended Audience :: Developers
Classifier: License :: OSI Approved :: MIT License
Classifier: Natural Language :: English
Classifier: Operating System :: POSIX
Classifier: Operating System :: Microsoft :: Windows
Classifier: Programming Language :: Python :: 3
Classifier: Programming Language :: Python :: 3.8
Classifier: Programming Language :: Python :: 3.9
Classifier: Programming Language :: Python :: 3.10
Classifier: Programming Language :: Python :: 3.11
Requires-Python: >=3.8
License-File: COPYING
License-File: AUTHORS.rst
Requires-Dist: colorama
Requires-Dist: pefile
Requires-Dist: Jinja2
